azureml/__init__.py
azureml/serving/__init__.py
azureml/serving/modeldatacollector.py
azureml/serving/tools/modeldatacollector/lib/native/Darwin/libazurestorage.3.0.dylib
azureml/serving/tools/modeldatacollector/lib/native/Darwin/libazurestorage.3.dylib
azureml/serving/tools/modeldatacollector/lib/native/Darwin/libazurestorage.dylib
azureml/serving/tools/modeldatacollector/lib/native/Darwin/libboost_atomic.dylib
azureml/serving/tools/modeldatacollector/lib/native/Darwin/libboost_chrono.dylib
azureml/serving/tools/modeldatacollector/lib/native/Darwin/libboost_container.dylib
azureml/serving/tools/modeldatacollector/lib/native/Darwin/libboost_context.dylib
azureml/serving/tools/modeldatacollector/lib/native/Darwin/libboost_coroutine.dylib
azureml/serving/tools/modeldatacollector/lib/native/Darwin/libboost_date_time.dylib
azureml/serving/tools/modeldatacollector/lib/native/Darwin/libboost_filesystem.dylib
azureml/serving/tools/modeldatacollector/lib/native/Darwin/libboost_graph.dylib
azureml/serving/tools/modeldatacollector/lib/native/Darwin/libboost_iostreams.dylib
azureml/serving/tools/modeldatacollector/lib/native/Darwin/libboost_locale.dylib
azureml/serving/tools/modeldatacollector/lib/native/Darwin/libboost_log.dylib
azureml/serving/tools/modeldatacollector/lib/native/Darwin/libboost_log_setup.dylib
azureml/serving/tools/modeldatacollector/lib/native/Darwin/libboost_math_c99.dylib
azureml/serving/tools/modeldatacollector/lib/native/Darwin/libboost_math_c99f.dylib
azureml/serving/tools/modeldatacollector/lib/native/Darwin/libboost_math_c99l.dylib
azureml/serving/tools/modeldatacollector/lib/native/Darwin/libboost_math_tr1.dylib
azureml/serving/tools/modeldatacollector/lib/native/Darwin/libboost_math_tr1f.dylib
azureml/serving/tools/modeldatacollector/lib/native/Darwin/libboost_math_tr1l.dylib
azureml/serving/tools/modeldatacollector/lib/native/Darwin/libboost_prg_exec_monitor.dylib
azureml_serving-0.1.0a14.dist-info/DESCRIPTION.rst
azureml_serving-0.1.0a14.dist-info/METADATA
azureml_serving-0.1.0a14.dist-info/RECORD
azureml_serving-0.1.0a14.dist-info/WHEEL
azureml_serving-0.1.0a14.dist-info/metadata.json
azureml_serving-0.1.0a14.dist-info/top_level.txt
